CPCLI/__init__.py
CPCLI/core.py
CPCLI/file_filtering_functions.py
CPCLI/utils.py
CPCLI/decorator/__init__.py
CPCLI/overall_processing_function/__init__.py
CPCLI/overall_processing_function/_future_top.py
CPCLI/overall_processing_function/group.py
CPCLI/processing_function/__init__.py
CPCLI/processing_function/addhead.py
CPCLI/processing_function/delete_blank_lines.py
CPCLI/processing_function/delete_useless_strings.py
CP_CLI-1.0.3.dist-info/LICENSE
CP_CLI-1.0.3.dist-info/METADATA
CP_CLI-1.0.3.dist-info/WHEEL
CP_CLI-1.0.3.dist-info/top_level.txt
CP_CLI-1.0.3.dist-info/RECORD
