Metadata-Version: 2.1
Name: CP-CLI
Version: 1.0.3
Summary: python 打包编译工具
Home-page: https://github.com/cpcgskill/CPCLI
Author: cpcgskill
Author-email: cpcgskill@outlook.com
License: Apache Software License (Apache 2.0)
Project-URL: Bug Tracker, https://github.com/cpcgskill/CPCLI/issues
Platform: UNKNOWN
Classifier: License :: OSI Approved :: Apache Software License
Classifier: Programming Language :: Python
Classifier: Programming Language :: Python :: 2
Classifier: Programming Language :: Python :: 2.7
Classifier: Programming Language :: Python :: Implementation :: CPython
Requires-Python: ==2.*,
License-File: LICENSE
Requires-Dist: astunparse (==1.6.3)
